airfoils/__init__.py
airfoils/__version__.py
airfoils/airfoils.py
airfoils/fileio.py
airfoils-0.2.2.dist-info/LICENSE.txt
airfoils-0.2.2.dist-info/METADATA
airfoils-0.2.2.dist-info/WHEEL
airfoils-0.2.2.dist-info/top_level.txt
airfoils-0.2.2.dist-info/RECORD
