Metadata-Version: 2.1
Name: airfoils
Version: 0.2.2
Summary: Airfoils (aerofoils)
Home-page: https://github.com/airinnova/airfoils
Author: Aaron Dettmann
Author-email: dettmann@kth.se
License: Apache License 2.0
Platform: UNKNOWN
Classifier: Programming Language :: Python :: 3
Classifier: Programming Language :: Python :: 3.6
Classifier: License :: OSI Approved :: Apache Software License
Classifier: Operating System :: OS Independent
Classifier: Environment :: Console
Classifier: Intended Audience :: Developers
Classifier: Intended Audience :: Education
Classifier: Intended Audience :: Science/Research
Classifier: Topic :: Scientific/Engineering
Classifier: Topic :: Scientific/Engineering :: Physics
Requires-Python: >=3.6.0
Requires-Dist: matplotlib
Requires-Dist: numpy
Requires-Dist: scipy
